chandra/__init__.py
chandra/input.py
chandra/output.py
chandra/prompts.py
chandra/settings.py
chandra/util.py
chandra/model/__init__.py
chandra/model/hf.py
chandra/model/schema.py
chandra/model/util.py
chandra/model/vllm.py
chandra/scripts/__init__.py
chandra/scripts/app.py
chandra/scripts/cli.py
chandra/scripts/run_app.py
chandra/scripts/screenshot_app.py
chandra/scripts/vllm.py
chandra_ocr-0.1.7.dist-info/licenses/LICENSE
chandra_ocr-0.1.7.dist-info/METADATA
chandra_ocr-0.1.7.dist-info/WHEEL
chandra_ocr-0.1.7.dist-info/entry_points.txt
chandra_ocr-0.1.7.dist-info/top_level.txt
chandra_ocr-0.1.7.dist-info/RECORD
