Metadata-Version: 2.4
Name: chandra-ocr
Version: 0.1.7
Summary: OCR model that converts documents to markdown, HTML, or JSON.
Author-email: Datalab <hi@datalab.to>
License: Apache-2.0
Keywords: ocr,pdf,markdown,layout
Requires-Python: >=3.10
License-File: LICENSE
Requires-Dist: beautifulsoup4>=4.14.2
Requires-Dist: click>=8.0.0
Requires-Dist: filetype>=1.2.0
Requires-Dist: flask>=3.0.0
Requires-Dist: markdownify==1.1.0
Requires-Dist: openai>=2.2.0
Requires-Dist: pillow>=10.2.0
Requires-Dist: pydantic>=2.12.0
Requires-Dist: pydantic-settings>=2.11.0
Requires-Dist: pypdfium2>=4.30.0
Requires-Dist: python-dotenv>=1.1.1
Requires-Dist: qwen-vl-utils>=0.0.14
Requires-Dist: torch>=2.8.0
Requires-Dist: torchvision>=0.23.0
Requires-Dist: transformers>=4.57.1
Requires-Dist: streamlit>=1.50.0
Requires-Dist: accelerate>=1.11.0
Dynamic: license-file
